[
  {
    "count": "333105", 
    "page": "Main Page"
  }, 
  {
    "count": "171071", 
    "page": "Special:Search"
  }, 
  {
    "count": "149469", 
    "page": "Special:Random"
  }, 
  {
    "count": "23665", 
    "page": "File:Tora no o wo fumu otokotachi poster.jpg"
  }, 
  {
    "count": "11872", 
    "page": "Main Page Test"
  }, 
  {
    "count": "11483", 
    "page": "Mullet (haircut)"
  }, 
  {
    "count": "9243", 
    "page": "List of IIT JEE Toppers"
  }, 
  {
    "count": "8179", 
    "page": "Special:OAIRepository"
  }, 
  {
    "count": "7310", 
    "page": "Main Page/"
  }, 
  {
    "count": "6921", 
    "page": "404 error"
  }, 
  {
    "count": "5790", 
    "page": "Hanna (film)"
  }, 
  {
    "count": "5506", 
    "page": "Project X (2012 film)"
  }, 
  {
    "count": "5256", 
    "page": "The Hunger Games"
  }, 
  {
    "count": "5076", 
    "page": "Strikeforce: Tate vs. Rousey"
  }, 
  {
    "count": "4936", 
    "page": "The Godfather"
  }, 
  {
    "count": "4881", 
    "page": "Singing"
  }, 
  {
    "count": "4807", 
    "page": "Susan Wright (murderer)"
  }, 
  {
    "count": "4475", 
    "page": "Hugo (film)"
  }, 
  {
    "count": "4273", 
    "page": "One Direction"
  }, 
  {
    "count": "4200", 
    "page": "Facebook"
  }, 
  {
    "count": "3821", 
    "page": "Special:Watchlist"
  }, 
  {
    "count": "3795", 
    "page": "File:ThreeGorgesDam-China2009.jpg"
  }, 
  {
    "count": "3750", 
    "page": "J. Edgar Hoover"
  }, 
  {
    "count": "3692", 
    "page": "1989 Belgian MiG-23 crash"
  }, 
  {
    "count": "3534", 
    "page": "The Monkees"
  }, 
  {
    "count": "3499", 
    "page": "Davy Jones (musician)"
  }, 
  {
    "count": "3292", 
    "page": "Susan Wright"
  }, 
  {
    "count": "3204", 
    "page": "Ondine's curse"
  }, 
  {
    "count": "3124", 
    "page": "Doc Rivers"
  }, 
  {
    "count": "3123", 
    "page": "The Big Bang Theory"
  }, 
  {
    "count": "3027", 
    "page": "Wiki"
  }, 
  {
    "count": "3021", 
    "page": "The Lorax"
  }, 
  {
    "count": "3011", 
    "page": "Marilyn Monroe"
  }, 
  {
    "count": "2824", 
    "page": "Dr. Seuss"
  }, 
  {
    "count": "2815", 
    "page": "The Godfather Part II"
  }, 
  {
    "count": "2751", 
    "page": "North Sentinel Island"
  }, 
  {
    "count": "2681", 
    "page": "Deaths in 2012"
  }, 
  {
    "count": "2581", 
    "page": "Wil Wheaton"
  }, 
  {
    "count": "2549", 
    "page": "Kirk Cameron"
  }, 
  {
    "count": "2489", 
    "page": "Wikipedia:IPA for English"
  }, 
  {
    "count": "2445", 
    "page": "The Godfather Saga"
  }, 
  {
    "count": "2441", 
    "page": "Victorious"
  }, 
  {
    "count": "2406", 
    "page": "Rush Limbaugh"
  }, 
  {
    "count": "2388", 
    "page": "Ryan Couture"
  }, 
  {
    "count": "2379", 
    "page": "Adele (singer)"
  }, 
  {
    "count": "2366", 
    "page": "Miles Plumlee"
  }, 
  {
    "count": "2295", 
    "page": "Saoirse Ronan"
  }, 
  {
    "count": "2223", 
    "page": "Jesse Stone (character)"
  }, 
  {
    "count": "2136", 
    "page": "Jennifer Lopez"
  }, 
  {
    "count": "2112", 
    "page": "The Dark Knight (film)"
  }, 
  {
    "count": "2076", 
    "page": "Cuisinart"
  }, 
  {
    "count": "2070", 
    "page": "Franchise tag"
  }, 
  {
    "count": "2065", 
    "page": "United States"
  }, 
  {
    "count": "2049", 
    "page": "Wladimir Klitschko"
  }, 
  {
    "count": "1995", 
    "page": "Google"
  }, 
  {
    "count": "1987", 
    "page": "Michael Nesmith"
  }, 
  {
    "count": "1970", 
    "page": "Rutherford B. Hayes"
  }, 
  {
    "count": "1961", 
    "page": "Smash (TV series)"
  }, 
  {
    "count": "1935", 
    "page": "The Avengers (2012 film)"
  }, 
  {
    "count": "1908", 
    "page": "How I Met Your Mother"
  }, 
  {
    "count": "1902", 
    "page": "Heath Ledger"
  }, 
  {
    "count": "1868", 
    "page": "The Artist (film)"
  }, 
  {
    "count": "1862", 
    "page": "Billy Beane"
  }, 
  {
    "count": "1850", 
    "page": "Seven deadly sins"
  }, 
  {
    "count": "1842", 
    "page": "GCB (TV series)"
  }, 
  {
    "count": "1829", 
    "page": "Justin Bieber"
  }, 
  {
    "count": "1810", 
    "page": "Robert De Niro"
  }, 
  {
    "count": "1805", 
    "page": "Wilt Chamberlain"
  }, 
  {
    "count": "1783", 
    "page": "Tokyo Sky Tree"
  }, 
  {
    "count": "1781", 
    "page": "Storage Wars"
  }, 
  {
    "count": "1762", 
    "page": "Mike Krzyzewski"
  }, 
  {
    "count": "1759", 
    "page": "The Walking Dead (TV series)"
  }, 
  {
    "count": "1758", 
    "page": "Skrillex"
  }, 
  {
    "count": "1750", 
    "page": "Austin Rivers"
  }, 
  {
    "count": "1746", 
    "page": "Office Space"
  }, 
  {
    "count": "1745", 
    "page": "The Lorax (film)"
  }, 
  {
    "count": "1743", 
    "page": "Sex"
  }, 
  {
    "count": "1731", 
    "page": "List of Victorious episodes"
  }, 
  {
    "count": "1690", 
    "page": "Some Like It Hot"
  }, 
  {
    "count": "1673", 
    "page": "Ronda Rousey"
  }, 
  {
    "count": "1671", 
    "page": "The Dark Knight Rises"
  }, 
  {
    "count": "1669", 
    "page": "Pando (tree)"
  }, 
  {
    "count": "1668", 
    "page": "Syd Barrett"
  }, 
  {
    "count": "1664", 
    "page": "Special:FeedItem/featured/20120304000000/en"
  }, 
  {
    "count": "1664", 
    "page": "Howard Hughes"
  }, 
  {
    "count": "1642", 
    "page": "Tom Selleck"
  }, 
  {
    "count": "1634", 
    "page": "Don Cherry"
  }, 
  {
    "count": "1627", 
    "page": "Randy Carlyle"
  }, 
  {
    "count": "1621", 
    "page": "Neil Armstrong"
  }, 
  {
    "count": "1615", 
    "page": "UFC on FX: Alves vs. Kampmann"
  }, 
  {
    "count": "1613", 
    "page": "Downton Abbey"
  }, 
  {
    "count": "1612", 
    "page": "Special:FeedItem/potd/20120304000000/en"
  }, 
  {
    "count": "1611", 
    "page": "Pink Floyd"
  }, 
  {
    "count": "1574", 
    "page": "The Godfather Part III"
  }, 
  {
    "count": "1569", 
    "page": "List of The Big Bang Theory episodes"
  }, 
  {
    "count": "1567", 
    "page": "The Texas Chain Saw Massacre"
  }, 
  {
    "count": "1562", 
    "page": "Prostitution in Africa"
  }, 
  {
    "count": "1562", 
    "page": "John Carter (character)"
  }, 
  {
    "count": "1558", 
    "page": "Margaret Thatcher"
  }, 
  {
    "count": "1555", 
    "page": "List of unusual deaths"
  }, 
  {
    "count": "1552", 
    "page": "Game of Thrones (TV series)"
  }, 
  {
    "count": "1551", 
    "page": "Seth Curry"
  }, 
  {
    "count": "1521", 
    "page": "Marc Anthony"
  }, 
  {
    "count": "1520", 
    "page": "Rihanna"
  }, 
  {
    "count": "1517", 
    "page": "Mason Plumlee"
  }, 
  {
    "count": "1510", 
    "page": "Miesha Tate"
  }, 
  {
    "count": "1501", 
    "page": "Wsearch.php"
  }, 
  {
    "count": "1501", 
    "page": "Nicki Minaj"
  }, 
  {
    "count": "1497", 
    "page": "How to Rock"
  }, 
  {
    "count": "1491", 
    "page": "Special:FeedItem/onthisday/20120304000000/en"
  }, 
  {
    "count": "1479", 
    "page": "Portal:Current events"
  }, 
  {
    "count": "1475", 
    "page": "The Hunger Games (film)"
  }, 
  {
    "count": "1475", 
    "page": "Al Pacino"
  }, 
  {
    "count": "1474", 
    "page": "Andrew Breitbart"
  }, 
  {
    "count": "1469", 
    "page": "AFI's 100 Years...100 Movie Quotes"
  }, 
  {
    "count": "1462", 
    "page": "Mary Winkler"
  }, 
  {
    "count": "1454", 
    "page": "Selena Gomez"
  }, 
  {
    "count": "1440", 
    "page": "Gold Jewelry"
  }, 
  {
    "count": "1435", 
    "page": "Nicole Polizzi"
  }, 
  {
    "count": "1426", 
    "page": "Eminem"
  }, 
  {
    "count": "1414", 
    "page": "Jersey Shore (TV series)"
  }, 
  {
    "count": "1411", 
    "page": "USS Cyclops (AC-4)"
  }, 
  {
    "count": "1406", 
    "page": "Duke University"
  }, 
  {
    "count": "1403", 
    "page": "Lady Gaga"
  }, 
  {
    "count": "1389", 
    "page": "Lost in Space"
  }, 
  {
    "count": "1389", 
    "page": "Juno (film)"
  }, 
  {
    "count": "1379", 
    "page": "Krummlauf"
  }, 
  {
    "count": "1376", 
    "page": "Jeremy Lin"
  }, 
  {
    "count": "1358", 
    "page": "Cirque du Freak: The Vampire's Assistant"
  }, 
  {
    "count": "1346", 
    "page": "Mass Effect 3"
  }, 
  {
    "count": "1343", 
    "page": "Whitney Houston"
  }, 
  {
    "count": "1331", 
    "page": "List of Young Justice episodes"
  }, 
  {
    "count": "1328", 
    "page": "Ralph McQuarrie"
  }, 
  {
    "count": "1315", 
    "page": "National Treasure (film)"
  }, 
  {
    "count": "1310", 
    "page": "Barry Weiss"
  }, 
  {
    "count": "1292", 
    "page": "Adam Levine"
  }, 
  {
    "count": "1291", 
    "page": "List of My Little Pony: Friendship Is Magic episodes"
  }, 
  {
    "count": "1290", 
    "page": "Mark Zuckerberg"
  }, 
  {
    "count": "1287", 
    "page": "Pornography"
  }, 
  {
    "count": "1285", 
    "page": "Angelina Jolie"
  }, 
  {
    "count": "1282", 
    "page": "Wikipedia:Picture of the day"
  }, 
  {
    "count": "1282", 
    "page": "Illuminati"
  }, 
  {
    "count": "1282", 
    "page": "Georges M\u00e9li\u00e8s"
  }, 
  {
    "count": "1282", 
    "page": "George Clooney"
  }, 
  {
    "count": "1277", 
    "page": "YouTube"
  }, 
  {
    "count": "1277", 
    "page": "Boyz n the Hood"
  }, 
  {
    "count": "1272", 
    "page": "John Carter (film)"
  }, 
  {
    "count": "1257", 
    "page": "Micky Dolenz"
  }, 
  {
    "count": "1250", 
    "page": "Carolina\u2013Duke rivalry"
  }, 
  {
    "count": "1249", 
    "page": "File:Courbet Sleep.jpg"
  }, 
  {
    "count": "1243", 
    "page": "Gotye"
  }, 
  {
    "count": "1238", 
    "page": "Act of Valor"
  }, 
  {
    "count": "1236", 
    "page": "Glee (TV series)"
  }, 
  {
    "count": "1234", 
    "page": "Sara Paxton"
  }, 
  {
    "count": "1229", 
    "page": "Marisa Tomei"
  }, 
  {
    "count": "1220", 
    "page": "Angie Everhart"
  }, 
  {
    "count": "1204", 
    "page": "Vanessa Minnillo"
  }, 
  {
    "count": "1202", 
    "page": "Sandra Fluke"
  }, 
  {
    "count": "1178", 
    "page": "Lil Wayne"
  }, 
  {
    "count": "1175", 
    "page": "LMFAO (group)"
  }, 
  {
    "count": "1172", 
    "page": "The Girl with the Dragon Tattoo"
  }, 
  {
    "count": "1170", 
    "page": "Alice in Wonderland (2010 film)"
  }, 
  {
    "count": "1165", 
    "page": "Vitali Klitschko"
  }, 
  {
    "count": "1159", 
    "page": "Michael Jordan"
  }, 
  {
    "count": "1158", 
    "page": "A Bridge Too Far (film)"
  }, 
  {
    "count": "1156", 
    "page": "Jim Parsons"
  }, 
  {
    "count": "1156", 
    "page": ".xxx"
  }, 
  {
    "count": "1149", 
    "page": "World War II"
  }, 
  {
    "count": "1147", 
    "page": "Cameron Indoor Stadium"
  }, 
  {
    "count": "1144", 
    "page": "Lindenhurst, New York"
  }, 
  {
    "count": "1142", 
    "page": "Kaley Cuoco"
  }, 
  {
    "count": "1139", 
    "page": "Johnny Depp"
  }, 
  {
    "count": "1134", 
    "page": "Stephen hawkings"
  }, 
  {
    "count": "1134", 
    "page": "Loretta Lynn"
  }, 
  {
    "count": "1133", 
    "page": "Kurt Russell"
  }, 
  {
    "count": "1130", 
    "page": "Wikipedia"
  }, 
  {
    "count": "1130", 
    "page": "Dwayne Johnson"
  }, 
  {
    "count": "1126", 
    "page": "Eurofighter Typhoon"
  }, 
  {
    "count": "1122", 
    "page": "Peter Tork"
  }, 
  {
    "count": "1116", 
    "page": "Rick Santorum"
  }, 
  {
    "count": "1115", 
    "page": "w/index.php"
  }, 
  {
    "count": "1115", 
    "page": "Ted Kaczynski"
  }, 
  {
    "count": "1107", 
    "page": "Special:Export/Insurance policy"
  }, 
  {
    "count": "1107", 
    "page": "Barack Obama"
  }, 
  {
    "count": "1106", 
    "page": "Jennifer Aniston"
  }, 
  {
    "count": "1106", 
    "page": "Burj Khalifa"
  }, 
  {
    "count": "1105", 
    "page": "White Chicks"
  }, 
  {
    "count": "1101", 
    "page": "Republican Party presidential primaries, 2012"
  }, 
  {
    "count": "1099", 
    "page": "Pat Healy (fighter)"
  }, 
  {
    "count": "1084", 
    "page": "Drive (2011 film)"
  }, 
  {
    "count": "1079", 
    "page": "Doug Furnas"
  }, 
  {
    "count": "1078", 
    "page": "Adolf Hitler"
  }, 
  {
    "count": "1072", 
    "page": "Cee Lo Green"
  }, 
  {
    "count": "1069", 
    "page": "Mila Kunis"
  }, 
  {
    "count": "1065", 
    "page": "Marlon Brando"
  }, 
  {
    "count": "1062", 
    "page": "Taylor Swift"
  }, 
  {
    "count": "1055", 
    "page": "Project X"
  }, 
  {
    "count": "1054", 
    "page": "March 3"
  }, 
  {
    "count": "1052", 
    "page": "Queen Victoria"
  }, 
  {
    "count": "1051", 
    "page": "Katy Perry"
  }, 
  {
    "count": "1050", 
    "page": "UFC 145"
  }, 
  {
    "count": "1049", 
    "page": "Sacha Baron Cohen"
  }, 
  {
    "count": "1049", 
    "page": "Hocus Pocus (1993 film)"
  }, 
  {
    "count": "1049", 
    "page": "Ellen Page"
  }, 
  {
    "count": "1045", 
    "page": "Josh Hutcherson"
  }, 
  {
    "count": "1040", 
    "page": "Jennifer Lawrence"
  }, 
  {
    "count": "1039", 
    "page": "Roy Williams (coach)"
  }, 
  {
    "count": "1038", 
    "page": "Sean Parker"
  }, 
  {
    "count": "1036", 
    "page": "List of How I Met Your Mother episodes"
  }, 
  {
    "count": "1035", 
    "page": "March 4"
  }, 
  {
    "count": "1035", 
    "page": "Cymphonique Miller"
  }, 
  {
    "count": "1034", 
    "page": "List of Presidents of the United States"
  }, 
  {
    "count": "1033", 
    "page": "Nicolas Cage"
  }, 
  {
    "count": "1028", 
    "page": "2012 in film"
  }, 
  {
    "count": "1024", 
    "page": "Lindsay Lohan"
  }, 
  {
    "count": "1021", 
    "page": "Vito Corleone"
  }, 
  {
    "count": "1017", 
    "page": "UFC 144"
  }, 
  {
    "count": "1016", 
    "page": "List of Glee episodes"
  }, 
  {
    "count": "1016", 
    "page": "Lana Del Rey"
  }, 
  {
    "count": "1004", 
    "page": "Grimm (TV series)"
  }, 
  {
    "count": "1002", 
    "page": "Madonna (entertainer)"
  }, 
  {
    "count": "997", 
    "page": "Katharine McPhee"
  }, 
  {
    "count": "993", 
    "page": "Bruce Lee"
  }, 
  {
    "count": "990", 
    "page": "Drake (entertainer)"
  }, 
  {
    "count": "987", 
    "page": "Supernatural (TV series)"
  }, 
  {
    "count": "986", 
    "page": "Brad Pitt"
  }, 
  {
    "count": "985", 
    "page": "Ryan Gosling"
  }, 
  {
    "count": "984", 
    "page": "Young Justice (TV series)"
  }, 
  {
    "count": "984", 
    "page": "SCUM Manifesto"
  }, 
  {
    "count": "979", 
    "page": "Jean Shrimpton"
  }, 
  {
    "count": "979", 
    "page": "Grand Canyon"
  }, 
  {
    "count": "978", 
    "page": "Freemasonry"
  }, 
  {
    "count": "977", 
    "page": "Doris Day"
  }, 
  {
    "count": "975", 
    "page": "Internet Movie Database"
  }, 
  {
    "count": "969", 
    "page": "Tyler Zeller"
  }, 
  {
    "count": "966", 
    "page": "List of Top Gear episodes"
  }, 
  {
    "count": "962", 
    "page": "United States non-interventionism"
  }, 
  {
    "count": "959", 
    "page": "Elizabeth II"
  }, 
  {
    "count": "956", 
    "page": "World War I"
  }, 
  {
    "count": "955", 
    "page": "Sons of Guns"
  }, 
  {
    "count": "954", 
    "page": "Once Upon a Time (TV series)"
  }, 
  {
    "count": "954", 
    "page": "Big Time Rush"
  }, 
  {
    "count": "948", 
    "page": "The Help (film)"
  }, 
  {
    "count": "946", 
    "page": "Stephen Curry (basketball)"
  }, 
  {
    "count": "943", 
    "page": "Christian Bale"
  }, 
  {
    "count": "936", 
    "page": "NCAA Men's Division I Basketball Championship"
  }, 
  {
    "count": "936", 
    "page": "Mitt Romney"
  }, 
  {
    "count": "935", 
    "page": "Tupac Shakur"
  }, 
  {
    "count": "932", 
    "page": "Kim Kardashian"
  }, 
  {
    "count": "927", 
    "page": "The Wanted"
  }, 
  {
    "count": "922", 
    "page": "Human penis size"
  }, 
  {
    "count": "920", 
    "page": "Jessie (TV series)"
  }, 
  {
    "count": "919", 
    "page": "Kobe Bryant"
  }, 
  {
    "count": "917", 
    "page": "Puss in Boots (2011 film)"
  }, 
  {
    "count": "917", 
    "page": "Gemini 4"
  }, 
  {
    "count": "914", 
    "page": "Batman"
  }, 
  {
    "count": "913", 
    "page": "Tornado"
  }, 
  {
    "count": "910", 
    "page": "Canada"
  }, 
  {
    "count": "909", 
    "page": "Revenge (TV series)"
  }, 
  {
    "count": "906", 
    "page": "Tom Hardy"
  }, 
  {
    "count": "906", 
    "page": "Christina Aguilera"
  }, 
  {
    "count": "906", 
    "page": "Ariana Grande"
  }, 
  {
    "count": "903", 
    "page": "Pirates of the Caribbean (film series)"
  }, 
  {
    "count": "902", 
    "page": "Wiz Khalifa"
  }, 
  {
    "count": "900", 
    "page": "Tony Curtis"
  }, 
  {
    "count": "899", 
    "page": "Meryl Streep"
  }, 
  {
    "count": "899", 
    "page": "Leather Guitar Strap"
  }, 
  {
    "count": "897", 
    "page": "Immortals (2011 film)"
  }, 
  {
    "count": "894", 
    "page": "Lucille Ball"
  }, 
  {
    "count": "891", 
    "page": "Assassin's Creed"
  }, 
  {
    "count": "890", 
    "page": "Spartacus: Vengeance"
  }, 
  {
    "count": "888", 
    "page": "List of The Walking Dead episodes"
  }, 
  {
    "count": "887", 
    "page": "National Treasure (franchise)"
  }, 
  {
    "count": "886", 
    "page": "Windows 8"
  }, 
  {
    "count": "884", 
    "page": "Toronto Maple Leafs"
  }, 
  {
    "count": "880", 
    "page": "Robin van Persie"
  }, 
  {
    "count": "879", 
    "page": "The Last Samurai"
  }, 
  {
    "count": "879", 
    "page": "Portal:Contents"
  }, 
  {
    "count": "878", 
    "page": "North Carolina Tar Heels men's basketball"
  }, 
  {
    "count": "877", 
    "page": "File:Chicago sunrise 1.jpg"
  }, 
  {
    "count": "871", 
    "page": "Sherlock (TV series)"
  }, 
  {
    "count": "870", 
    "page": "Duke Blue Devils men's basketball"
  }, 
  {
    "count": "869", 
    "page": "New Jersey Photographer"
  }, 
  {
    "count": "867", 
    "page": "Chronicle (film)"
  }, 
  {
    "count": "866", 
    "page": "84th Academy Awards"
  }, 
  {
    "count": "864", 
    "page": "Elizabeth Gillies"
  }, 
  {
    "count": "863", 
    "page": "Jeffrey Dahmer"
  }, 
  {
    "count": "860", 
    "page": "Victoria Justice"
  }, 
  {
    "count": "859", 
    "page": "Rowan Atkinson"
  }, 
  {
    "count": "859", 
    "page": "Beyonc\u00e9 Knowles"
  }, 
  {
    "count": "858", 
    "page": "Alouette (song)"
  }, 
  {
    "count": "857", 
    "page": "Gnarls Barkley"
  }, 
  {
    "count": "856", 
    "page": "Lamar Odom"
  }, 
  {
    "count": "852", 
    "page": "Zebrafish"
  }, 
  {
    "count": "852", 
    "page": "Breaking Bad"
  }, 
  {
    "count": "851", 
    "page": "Special:Export/"
  }, 
  {
    "count": "851", 
    "page": "Spartacus"
  }, 
  {
    "count": "849", 
    "page": "Elizabeth I of England"
  }, 
  {
    "count": "843", 
    "page": "Uno (card game)"
  }, 
  {
    "count": "840", 
    "page": "Rachael Ray"
  }, 
  {
    "count": "839", 
    "page": "The Walking Dead (season 2)"
  }, 
  {
    "count": "836", 
    "page": "Jessica Biel"
  }, 
  {
    "count": "836", 
    "page": "Bioinformatic Harvester"
  }, 
  {
    "count": "834", 
    "page": "Portal:Featured content"
  }, 
  {
    "count": "833", 
    "page": "New York City"
  }, 
  {
    "count": "833", 
    "page": "Fun (band)"
  }, 
  {
    "count": "830", 
    "page": "index.html"
  }, 
  {
    "count": "829", 
    "page": "Channing Tatum"
  }, 
  {
    "count": "828", 
    "page": "Merlin (TV series)"
  }, 
  {
    "count": "828", 
    "page": "Eduardo Saverin"
  }, 
  {
    "count": "827", 
    "page": "Doctor Who"
  }, 
  {
    "count": "827", 
    "page": "Alcatraz (TV series)"
  }, 
  {
    "count": "826", 
    "page": "Johnny Galecki"
  }, 
  {
    "count": "824", 
    "page": "The Beatles"
  }, 
  {
    "count": "816", 
    "page": "The Woman in Black (2012 film)"
  }, 
  {
    "count": "812", 
    "page": "Michael Jackson"
  }, 
  {
    "count": "810", 
    "page": "Alice's Adventures in Wonderland"
  }, 
  {
    "count": "808", 
    "page": "Vladimir Putin"
  }, 
  {
    "count": "805", 
    "page": "Tyga"
  }, 
  {
    "count": "803", 
    "page": "Star Wars"
  }, 
  {
    "count": "802", 
    "page": "The Girl with the Dragon Tattoo (2011 film)"
  }, 
  {
    "count": "799", 
    "page": "Street Fighter X Tekken"
  }, 
  {
    "count": "798", 
    "page": "The Vampire Diaries"
  }, 
  {
    "count": "796", 
    "page": "Lent"
  }, 
  {
    "count": "796", 
    "page": "Golf Bags"
  }, 
  {
    "count": "793", 
    "page": "List of emoticons"
  }, 
  {
    "count": "792", 
    "page": "Kevin Bacon"
  }, 
  {
    "count": "789", 
    "page": "Leonardo DiCaprio"
  }, 
  {
    "count": "786", 
    "page": "Youtube"
  }, 
  {
    "count": "786", 
    "page": "House (TV series)"
  }, 
  {
    "count": "786", 
    "page": "Archer (TV series)"
  }, 
  {
    "count": "785", 
    "page": "Star Trek (film)"
  }, 
  {
    "count": "785", 
    "page": "Saint Patrick's Day"
  }, 
  {
    "count": "783", 
    "page": "Chelsea Noble"
  }, 
  {
    "count": "779", 
    "page": "Wonders of the World"
  }, 
  {
    "count": "779", 
    "page": "Ides of March"
  }, 
  {
    "count": "777", 
    "page": "Minecraft"
  }, 
  {
    "count": "776", 
    "page": "C. Allan Gilbert"
  }, 
  {
    "count": "773", 
    "page": "John F. Kennedy"
  }, 
  {
    "count": "772", 
    "page": "Miley Cyrus"
  }, 
  {
    "count": "772", 
    "page": "Justin Timberlake"
  }, 
  {
    "count": "771", 
    "page": "United Kingdom"
  }, 
  {
    "count": "771", 
    "page": "RMS Titanic"
  }, 
  {
    "count": "771", 
    "page": "Assassin's Creed III"
  }, 
  {
    "count": "770", 
    "page": "Abraham Lincoln"
  }, 
  {
    "count": "766", 
    "page": "Moneyball (film)"
  }, 
  {
    "count": "763", 
    "page": "Adrienne Barbeau"
  }, 
  {
    "count": "762", 
    "page": "Jay-Z"
  }, 
  {
    "count": "759", 
    "page": "Demi Lovato"
  }, 
  {
    "count": "759", 
    "page": "Coccidioidomycosis"
  }, 
  {
    "count": "759", 
    "page": "Chlo\u00eb Moretz"
  }, 
  {
    "count": "758", 
    "page": "Awake (TV series)"
  }, 
  {
    "count": "756", 
    "page": "Moneyball"
  }, 
  {
    "count": "756", 
    "page": "Elvis Presley"
  }, 
  {
    "count": "755", 
    "page": "Westboro Baptist Church"
  }, 
  {
    "count": "755", 
    "page": "Mayim Bialik"
  }, 
  {
    "count": "755", 
    "page": "Kristin Chenoweth"
  }, 
  {
    "count": "754", 
    "page": "UFC on Fuel TV: Nogueira vs. Gustafsson"
  }, 
  {
    "count": "751", 
    "page": "Peter Clemenza"
  }, 
  {
    "count": "751", 
    "page": "Avengers (comics)"
  }, 
  {
    "count": "750", 
    "page": "Dubstep"
  }, 
  {
    "count": "749", 
    "page": "Amber Rose"
  }, 
  {
    "count": "748", 
    "page": "Harry Potter"
  }, 
  {
    "count": "745", 
    "page": "Fringe (TV series)"
  }, 
  {
    "count": "745", 
    "page": "Australia"
  }, 
  {
    "count": "742", 
    "page": "My Cousin Vinny"
  }, 
  {
    "count": "741", 
    "page": "List of Naruto: Shippuden episodes"
  }, 
  {
    "count": "740", 
    "page": "Choose Your Own Adventure: The Abominable Snowman"
  }, 
  {
    "count": "738", 
    "page": "Chuck Norris"
  }, 
  {
    "count": "737", 
    "page": "Caros Fodor"
  }, 
  {
    "count": "736", 
    "page": "Train (band)"
  }, 
  {
    "count": "736", 
    "page": "Pirates of the Caribbean"
  }, 
  {
    "count": "735", 
    "page": "Asperger syndrome"
  }, 
  {
    "count": "733", 
    "page": "Neil Patrick Harris"
  }, 
  {
    "count": "733", 
    "page": "Midnight in Paris"
  }, 
  {
    "count": "733", 
    "page": "Mariah Carey"
  }, 
  {
    "count": "732", 
    "page": "Ernest Hemingway"
  }, 
  {
    "count": "729", 
    "page": "Sex positions"
  }, 
  {
    "count": "728", 
    "page": "Pope Joan"
  }, 
  {
    "count": "727", 
    "page": "Wanted (2008 film)"
  }, 
  {
    "count": "725", 
    "page": "Early March 2012 tornado outbreak"
  }, 
  {
    "count": "725", 
    "page": "21 Jump Street"
  }, 
  {
    "count": "719", 
    "page": "A Song of Ice and Fire"
  }, 
  {
    "count": "718", 
    "page": "Sexual intercourse"
  }, 
  {
    "count": "717", 
    "page": "Randy Couture"
  }, 
  {
    "count": "715", 
    "page": "Kate Upton"
  }, 
  {
    "count": "713", 
    "page": "Transubstantiation"
  }, 
  {
    "count": "712", 
    "page": "Scarlett Johansson"
  }, 
  {
    "count": "712", 
    "page": "Charlie Sheen"
  }, 
  {
    "count": "712", 
    "page": "Brian Burke (ice hockey)"
  }, 
  {
    "count": "711", 
    "page": "List of Once Upon a Time episodes"
  }, 
  {
    "count": "708", 
    "page": "Stephen Hawking"
  }, 
  {
    "count": "707", 
    "page": "WrestleMania XXVIII"
  }, 
  {
    "count": "707", 
    "page": "Sof\u00eda Vergara"
  }, 
  {
    "count": "707", 
    "page": "Eddie Murphy"
  }, 
  {
    "count": "705", 
    "page": "Jack White (musician)"
  }, 
  {
    "count": "704", 
    "page": "Ren\u00e9 Descartes"
  }, 
  {
    "count": "704", 
    "page": "Adam Sandler"
  }, 
  {
    "count": "703", 
    "page": "Spartacus (2010 TV series)"
  }, 
  {
    "count": "702", 
    "page": "Peter Marshall (U.S. entertainer)"
  }, 
  {
    "count": "702", 
    "page": "Conor Heun"
  }, 
  {
    "count": "701", 
    "page": "Nick Clooney"
  }, 
  {
    "count": "700", 
    "page": "Rosemary Clooney"
  }, 
  {
    "count": "699", 
    "page": "The Apprentice (U.S. season 12)"
  }, 
  {
    "count": "699", 
    "page": "List of Fringe episodes"
  }, 
  {
    "count": "699", 
    "page": "Cirque du Freak"
  }, 
  {
    "count": "698", 
    "page": "Train Pocket Watch"
  }, 
  {
    "count": "698", 
    "page": "Sheldon Cooper"
  }, 
  {
    "count": "697", 
    "page": "Noel Gallagher"
  }, 
  {
    "count": "697", 
    "page": "Napoleon"
  }, 
  {
    "count": "696", 
    "page": "Reese Witherspoon"
  }, 
  {
    "count": "696", 
    "page": "Hanna"
  }, 
  {
    "count": "694", 
    "page": "Masturbation"
  }, 
  {
    "count": "692", 
    "page": "United States Declaration of Independence"
  }, 
  {
    "count": "692", 
    "page": "The Fifth Element"
  }, 
  {
    "count": "692", 
    "page": "Dolphin"
  }, 
  {
    "count": "691", 
    "page": "Zac Efron"
  }, 
  {
    "count": "689", 
    "page": "Zooey Deschanel"
  }, 
  {
    "count": "688", 
    "page": "Harry Potter (film series)"
  }, 
  {
    "count": "688", 
    "page": "Eliza Dushku"
  }, 
  {
    "count": "688", 
    "page": "Bruno Mars"
  }, 
  {
    "count": "687", 
    "page": "Inglourious Basterds"
  }, 
  {
    "count": "687", 
    "page": "Academy Award"
  }, 
  {
    "count": "686", 
    "page": "Blake Shelton"
  }, 
  {
    "count": "684", 
    "page": "Will Smith"
  }, 
  {
    "count": "683", 
    "page": "Catching Fire (2009 novel)"
  }, 
  {
    "count": "682", 
    "page": "Chris Brown (American entertainer)"
  }, 
  {
    "count": "681", 
    "page": "Vietnam War"
  }, 
  {
    "count": "681", 
    "page": "List of poker hands"
  }, 
  {
    "count": "681", 
    "page": "Bermuda Triangle"
  }, 
  {
    "count": "681", 
    "page": "Audrey Hepburn"
  }, 
  {
    "count": "680", 
    "page": "2012 phenomenon"
  }, 
  {
    "count": "679", 
    "page": "Strikeforce"
  }, 
  {
    "count": "679", 
    "page": "In Time"
  }, 
  {
    "count": "679", 
    "page": "HEARTLAND RVs"
  }, 
  {
    "count": "677", 
    "page": "India"
  }, 
  {
    "count": "675", 
    "page": "Wikipedia:Contact us"
  }, 
  {
    "count": "675", 
    "page": "Henry VIII of England"
  }, 
  {
    "count": "674", 
    "page": "Keenan Cahill"
  }, 
  {
    "count": "674", 
    "page": "Cate Blanchett"
  }, 
  {
    "count": "670", 
    "page": "Russia"
  }, 
  {
    "count": "669", 
    "page": "List of The Big Bang Theory characters"
  }, 
  {
    "count": "669", 
    "page": "Emma Stone"
  }, 
  {
    "count": "667", 
    "page": "Olivia Wilde"
  }, 
  {
    "count": "667", 
    "page": "Lindbergh kidnapping"
  }, 
  {
    "count": "667", 
    "page": "Japan"
  }, 
  {
    "count": "666", 
    "page": "List of United States cities by population"
  }, 
  {
    "count": "666", 
    "page": "Academy Award for Best Picture"
  }, 
  {
    "count": "664", 
    "page": "Diane Kruger"
  }, 
  {
    "count": "664", 
    "page": "Chicago"
  }, 
  {
    "count": "663", 
    "page": "Reba McEntire"
  }, 
  {
    "count": "663", 
    "page": "National Treasure: Book of Secrets"
  }, 
  {
    "count": "663", 
    "page": "China"
  }, 
  {
    "count": "662", 
    "page": "PlayStation Vita"
  }, 
  {
    "count": "661", 
    "page": "Truman Capote"
  }, 
  {
    "count": "661", 
    "page": "Ne-Yo"
  }, 
  {
    "count": "659", 
    "page": "Victoria Gotti"
  }, 
  {
    "count": "658", 
    "page": "Elaine Chao"
  }, 
  {
    "count": "657", 
    "page": "Vagina"
  }, 
  {
    "count": "657", 
    "page": "New Girl (TV series)"
  }, 
  {
    "count": "657", 
    "page": "ICarly"
  }, 
  {
    "count": "656", 
    "page": "This Means War (film)"
  }, 
  {
    "count": "653", 
    "page": "Windex.php"
  }, 
  {
    "count": "653", 
    "page": "Footloose (1984 film)"
  }, 
  {
    "count": "652", 
    "page": "2011 in film"
  }, 
  {
    "count": "650", 
    "page": "James Caan"
  }, 
  {
    "count": "649", 
    "page": "List of Revenge episodes"
  }, 
  {
    "count": "647", 
    "page": "The Voice (U.S.)"
  }, 
  {
    "count": "645", 
    "page": "Teigan Van Roosmalen"
  }, 
  {
    "count": "644", 
    "page": "Tom Cruise"
  }, 
  {
    "count": "643", 
    "page": "Lori Singer"
  }, 
  {
    "count": "643", 
    "page": "Goldie Hawn"
  }, 
  {
    "count": "641", 
    "page": "Ryan Reynolds"
  }, 
  {
    "count": "641", 
    "page": "Natalie Portman"
  }, 
  {
    "count": "639", 
    "page": "Sam Childers"
  }, 
  {
    "count": "639", 
    "page": "Megan Fox"
  }, 
  {
    "count": "639", 
    "page": "Jean Dujardin"
  }, 
  {
    "count": "639", 
    "page": "Dexter (TV series)"
  }, 
  {
    "count": "639", 
    "page": "Anal sex"
  }, 
  {
    "count": "638", 
    "page": "Carly Rae Jepsen"
  }, 
  {
    "count": "638", 
    "page": "Android (operating system)"
  }, 
  {
    "count": "637", 
    "page": "Mad Men"
  }, 
  {
    "count": "636", 
    "page": "Mark Wahlberg"
  }, 
  {
    "count": "635", 
    "page": "Modern Family"
  }, 
  {
    "count": "634", 
    "page": "Community (TV series)"
  }, 
  {
    "count": "634", 
    "page": "21 (Adele album)"
  }, 
  {
    "count": "633", 
    "page": "Frank Sinatra"
  }, 
  {
    "count": "633", 
    "page": "Clint Eastwood"
  }, 
  {
    "count": "632", 
    "page": "2011 NCAA Men's Division I Basketball Tournament"
  }, 
  {
    "count": "631", 
    "page": "The Tree of Life (film)"
  }, 
  {
    "count": "631", 
    "page": "Francis Ford Coppola"
  }, 
  {
    "count": "631", 
    "page": "2012 NCAA Men's Division I Basketball Tournament"
  }, 
  {
    "count": "630", 
    "page": "love story (1970 film)"
  }, 
  {
    "count": "630", 
    "page": "Grey's Anatomy"
  }, 
  {
    "count": "630", 
    "page": "Germany"
  }, 
  {
    "count": "630", 
    "page": "Eric Bana"
  }, 
  {
    "count": "630", 
    "page": "18k Gold Watch"
  }, 
  {
    "count": "629", 
    "page": "Kanye West"
  }, 
  {
    "count": "629", 
    "page": "Arnold Schwarzenegger"
  }, 
  {
    "count": "628", 
    "page": "2001: A Space Odyssey (film)"
  }, 
  {
    "count": "627", 
    "page": "Pretty Little Liars (TV series)"
  }, 
  {
    "count": "627", 
    "page": "Morgan Freeman"
  }, 
  {
    "count": "626", 
    "page": "Sons of Anarchy"
  }, 
  {
    "count": "625", 
    "page": "Muhammad Ali"
  }, 
  {
    "count": "625", 
    "page": "Mockingjay"
  }, 
  {
    "count": "625", 
    "page": "Albert Einstein"
  }, 
  {
    "count": "622", 
    "page": "Star Trek"
  }, 
  {
    "count": "619", 
    "page": "Ueno Station"
  }, 
  {
    "count": "619", 
    "page": "Ellen DeGeneres"
  }, 
  {
    "count": "619", 
    "page": "A Game of Thrones"
  }, 
  {
    "count": "618", 
    "page": "Psych"
  }, 
  {
    "count": "617", 
    "page": "50 Cent"
  }, 
  {
    "count": "616", 
    "page": "The Office (U.S. TV series)"
  }, 
  {
    "count": "616", 
    "page": "List of Doctor Who serials"
  }, 
  {
    "count": "615", 
    "page": "Super Tuesday"
  }, 
  {
    "count": "614", 
    "page": "UFC 146"
  }, 
  {
    "count": "614", 
    "page": "Le Sommeil"
  }, 
  {
    "count": "613", 
    "page": "Family Guy"
  }, 
  {
    "count": "612", 
    "page": "Titanic (1997 film)"
  }, 
  {
    "count": "612", 
    "page": "List of Grimm episodes"
  }, 
  {
    "count": "612", 
    "page": "Homeland (TV series)"
  }, 
  {
    "count": "611", 
    "page": "Jack Lemmon"
  }, 
  {
    "count": "610", 
    "page": "The Social Network"
  }, 
  {
    "count": "610", 
    "page": "Brazil"
  }, 
  {
    "count": "609", 
    "page": "How I Met Your Mother (season 7)"
  }, 
  {
    "count": "609", 
    "page": "Clyde Tolson"
  }, 
  {
    "count": "609", 
    "page": "Bob Marley"
  }, 
  {
    "count": "608", 
    "page": "Tornadoes of 2012"
  }, 
  {
    "count": "607", 
    "page": "Milla Jovovich"
  }, 
  {
    "count": "607", 
    "page": "Bruce Springsteen"
  }, 
  {
    "count": "606", 
    "page": "Tower Heist"
  }, 
  {
    "count": "606", 
    "page": "The Devil Inside (film)"
  }, 
  {
    "count": "603", 
    "page": "Scooby-Doo"
  }, 
  {
    "count": "603", 
    "page": "File:Orion Nebula - Hubble 2006 mosaic 18000.jpg"
  }, 
  {
    "count": "602", 
    "page": "The Vow (2012 film)"
  }, 
  {
    "count": "602", 
    "page": "List of songs in Glee (season 3)"
  }, 
  {
    "count": "602", 
    "page": "LeBron James"
  }, 
  {
    "count": "602", 
    "page": "Ice Cube"
  }, 
  {
    "count": "602", 
    "page": "Gary Oldman"
  }, 
  {
    "count": "601", 
    "page": "The Texas Chainsaw Massacre (2003 film)"
  }, 
  {
    "count": "600", 
    "page": "American Civil War"
  }, 
  {
    "count": "599", 
    "page": "The Silent House (film)"
  }, 
  {
    "count": "599", 
    "page": "Ronald Reagan"
  }, 
  {
    "count": "599", 
    "page": "Jesse Stone: Sea Change"
  }, 
  {
    "count": "598", 
    "page": "Cat"
  }, 
  {
    "count": "597", 
    "page": "Jesse Stone novels"
  }, 
  {
    "count": "595", 
    "page": "Rooney Mara"
  }, 
  {
    "count": "595", 
    "page": "Pretty in Pink"
  }, 
  {
    "count": "595", 
    "page": "Female ejaculation"
  }, 
  {
    "count": "593", 
    "page": "Two and a Half Men"
  }, 
  {
    "count": "593", 
    "page": "Ed Gein"
  }, 
  {
    "count": "592", 
    "page": "Bruce Willis"
  }, 
  {
    "count": "591", 
    "page": "Rachel McAdams"
  }, 
  {
    "count": "591", 
    "page": "List of iCarly episodes"
  }, 
  {
    "count": "588", 
    "page": "Kristen Stewart"
  }, 
  {
    "count": "587", 
    "page": "The Elder Scrolls V: Skyrim"
  }, 
  {
    "count": "587", 
    "page": "Go Topless Day"
  }, 
  {
    "count": "586", 
    "page": "List of House episodes"
  }, 
  {
    "count": "586", 
    "page": "Avril Lavigne"
  }, 
  {
    "count": "585", 
    "page": "Steve Jobs"
  }, 
  {
    "count": "585", 
    "page": "Daylight saving time"
  }, 
  {
    "count": "584", 
    "page": "Operation Market Garden"
  }, 
  {
    "count": "584", 
    "page": "Dog"
  }, 
  {
    "count": "584", 
    "page": "Britney Spears"
  }, 
  {
    "count": "583", 
    "page": "Penis"
  }, 
  {
    "count": "581", 
    "page": "Nick Jonas"
  }, 
  {
    "count": "581", 
    "page": "List of dog breeds"
  }, 
  {
    "count": "580", 
    "page": "Tyler, The Creator"
  }, 
  {
    "count": "578", 
    "page": "Vin Diesel"
  }, 
  {
    "count": "578", 
    "page": "My Little Pony: Friendship Is Magic"
  }, 
  {
    "count": "578", 
    "page": "Asa Butterfield"
  }, 
  {
    "count": "577", 
    "page": "American Idol"
  }, 
  {
    "count": "577", 
    "page": "Amanda Seyfried"
  }, 
  {
    "count": "576", 
    "page": "The Twilight Saga (film series)"
  }, 
  {
    "count": "576", 
    "page": "Something Borrowed (film)"
  }, 
  {
    "count": "574", 
    "page": "The Ides of March (film)"
  }, 
  {
    "count": "573", 
    "page": "X-Men (film series)"
  }, 
  {
    "count": "573", 
    "page": "Viola Davis"
  }, 
  {
    "count": "572", 
    "page": "The Undertaker"
  }, 
  {
    "count": "572", 
    "page": "List of Family Guy episodes"
  }, 
  {
    "count": "572", 
    "page": "Deadmau5"
  }, 
  {
    "count": "571", 
    "page": "Wipeout (2008 U.S. game show)"
  }, 
  {
    "count": "571", 
    "page": "J. Edgar"
  }, 
  {
    "count": "571", 
    "page": "Ivy League"
  }, 
  {
    "count": "571", 
    "page": "Henryville, Indiana"
  }, 
  {
    "count": "570", 
    "page": "Orion Nebula"
  }, 
  {
    "count": "568", 
    "page": "Basketball"
  }, 
  {
    "count": "565", 
    "page": "White Collar (TV series)"
  }, 
  {
    "count": "565", 
    "page": "Kate Hudson"
  }, 
  {
    "count": "565", 
    "page": "John Cena"
  }, 
  {
    "count": "564", 
    "page": "Tim Tebow"
  }, 
  {
    "count": "563", 
    "page": "Philippines"
  }, 
  {
    "count": "563", 
    "page": "Naruto"
  }, 
  {
    "count": "563", 
    "page": "Microsoft"
  }, 
  {
    "count": "563", 
    "page": "Iran\u2013Contra affair"
  }, 
  {
    "count": "563", 
    "page": "Dancing with the Stars (U.S. TV series)"
  }, 
  {
    "count": "562", 
    "page": "Tom Hanks"
  }, 
  {
    "count": "560", 
    "page": "The Temptations"
  }, 
  {
    "count": "560", 
    "page": "Seven (film)"
  }, 
  {
    "count": "560", 
    "page": "Ron Paul"
  }, 
  {
    "count": "559", 
    "page": "The Iron Lady (film)"
  }, 
  {
    "count": "559", 
    "page": "Scooby-Doo! Music of the Vampire"
  }, 
  {
    "count": "559", 
    "page": "List of Supernatural episodes"
  }, 
  {
    "count": "557", 
    "page": "Platypus"
  }, 
  {
    "count": "557", 
    "page": "Harrison Barnes"
  }, 
  {
    "count": "556", 
    "page": "Syria"
  }, 
  {
    "count": "555", 
    "page": "Twitter"
  }, 
  {
    "count": "555", 
    "page": "Ron Wilson (ice hockey b. 1955)"
  }, 
  {
    "count": "555", 
    "page": "Ron Livingston"
  }, 
  {
    "count": "555", 
    "page": "Liam Neeson"
  }, 
  {
    "count": "555", 
    "page": "Liam Hemsworth"
  }, 
  {
    "count": "555", 
    "page": "Footloose (2011 film)"
  }, 
  {
    "count": "554", 
    "page": "Wikipedia:Text of Creative Commons Attribution-ShareAlike 3.0 Unported License"
  }, 
  {
    "count": "554", 
    "page": "The Descendants (film)"
  }, 
  {
    "count": "553", 
    "page": "Hayden Panettiere"
  }, 
  {
    "count": "551", 
    "page": "Denzel Washington"
  }, 
  {
    "count": "551", 
    "page": "Betty White"
  }, 
  {
    "count": "550", 
    "page": "Marie Antoinette"
  }, 
  {
    "count": "550", 
    "page": "List of UFC events"
  }, 
  {
    "count": "550", 
    "page": "Christopher Plummer"
  }, 
  {
    "count": "549", 
    "page": "Matt Frattin"
  }, 
  {
    "count": "549", 
    "page": "Ghost Rider: Spirit of Vengeance"
  }, 
  {
    "count": "549", 
    "page": "George Washington"
  }, 
  {
    "count": "549", 
    "page": "Chris Pine"
  }, 
  {
    "count": "548", 
    "page": "Gout"
  }, 
  {
    "count": "546", 
    "page": "Secretariat (horse)"
  }, 
  {
    "count": "543", 
    "page": "Johnny Cash"
  }, 
  {
    "count": "542", 
    "page": "List of Greek mythological figures"
  }, 
  {
    "count": "541", 
    "page": "Toilet paper orientation"
  }, 
  {
    "count": "541", 
    "page": "PubMed Identifier"
  }, 
  {
    "count": "541", 
    "page": "Gwyneth Paltrow"
  }, 
  {
    "count": "541", 
    "page": "50/50 (2011 film)"
  }, 
  {
    "count": "540", 
    "page": "Debby Ryan"
  }, 
  {
    "count": "539", 
    "page": "The Notorious B.I.G."
  }, 
  {
    "count": "539", 
    "page": "Puerto Rico"
  }, 
  {
    "count": "539", 
    "page": "Journey 2: The Mysterious Island"
  }, 
  {
    "count": "538", 
    "page": "X-Men: First Class"
  }, 
  {
    "count": "538", 
    "page": "Kids Wallpaper"
  }, 
  {
    "count": "537", 
    "page": "The River (U.S. TV series)"
  }, 
  {
    "count": "537", 
    "page": "Pramface"
  }, 
  {
    "count": "536", 
    "page": "Coldplay"
  }, 
  {
    "count": "535", 
    "page": "Taylor Lautner"
  }, 
  {
    "count": "535", 
    "page": "Megan Hilty"
  }, 
  {
    "count": "534", 
    "page": "Belize"
  }, 
  {
    "count": "533", 
    "page": "George VI"
  }, 
  {
    "count": "533", 
    "page": "CSI: NY"
  }, 
  {
    "count": "532", 
    "page": "Shaquille O'Neal"
  }, 
  {
    "count": "531", 
    "page": "Rachel Weisz"
  }, 
  {
    "count": "531", 
    "page": "Oprah Winfrey"
  }, 
  {
    "count": "531", 
    "page": "Meme"
  }, 
  {
    "count": "530", 
    "page": "Mass Effect"
  }, 
  {
    "count": "530", 
    "page": "Joe Pesci"
  }, 
  {
    "count": "530", 
    "page": "Dick Vitale"
  }, 
  {
    "count": "529", 
    "page": "List of Running Man episodes"
  }, 
  {
    "count": "528", 
    "page": "Martin Scorsese"
  }, 
  {
    "count": "528", 
    "page": "Glee (season 3)"
  }, 
  {
    "count": "528", 
    "page": "Brittany Murphy"
  }, 
  {
    "count": "527", 
    "page": "Terra Nova (TV series)"
  }, 
  {
    "count": "527", 
    "page": "Hugo"
  }, 
  {
    "count": "527", 
    "page": "Amber Rose (model)"
  }, 
  {
    "count": "526", 
    "page": "Bruno Kirby"
  }, 
  {
    "count": "526", 
    "page": "American Idol (season 11)"
  }, 
  {
    "count": "525", 
    "page": "Tyler Hansbrough"
  }, 
  {
    "count": "525", 
    "page": "Pitbull (entertainer)"
  }, 
  {
    "count": "524", 
    "page": "Wish You Were Here (Pink Floyd album)"
  }, 
  {
    "count": "524", 
    "page": "Dinah Shore"
  }, 
  {
    "count": "523", 
    "page": "Stress Relief"
  }, 
  {
    "count": "523", 
    "page": "M.I.A. (artist)"
  }, 
  {
    "count": "522", 
    "page": "France"
  }, 
  {
    "count": "521", 
    "page": "Video Camera"
  }, 
  {
    "count": "521", 
    "page": "Cristiano Ronaldo"
  }, 
  {
    "count": "521", 
    "page": "Army Wives"
  }, 
  {
    "count": "520", 
    "page": "Raspberry Pi"
  }, 
  {
    "count": "520", 
    "page": "Bones (TV series)"
  }, 
  {
    "count": "519", 
    "page": "Netherlands"
  }, 
  {
    "count": "519", 
    "page": "MDMA"
  }, 
  {
    "count": "517", 
    "page": "Safe House (2012 film)"
  }, 
  {
    "count": "517", 
    "page": "Bee Gees"
  }, 
  {
    "count": "516", 
    "page": "Snoop Dogg"
  }, 
  {
    "count": "516", 
    "page": "Mike Tyson"
  }, 
  {
    "count": "516", 
    "page": "Lab Rats (TV series)"
  }, 
  {
    "count": "514", 
    "page": "List of House of Anubis episodes"
  }, 
  {
    "count": "514", 
    "page": "Erin Andrews"
  }, 
  {
    "count": "512", 
    "page": "The Mummy Returns"
  }, 
  {
    "count": "512", 
    "page": "List of Bleach episodes"
  }, 
  {
    "count": "512", 
    "page": "Kevin Durant"
  }, 
  {
    "count": "511", 
    "page": "Lost (TV series)"
  }, 
  {
    "count": "511", 
    "page": "Freddie Mercury"
  }, 
  {
    "count": "511", 
    "page": "File:Tokyo sky tree.jpg"
  }, 
  {
    "count": "510", 
    "page": "Wikipedia:About"
  }, 
  {
    "count": "510", 
    "page": "Saturday Night Live"
  }, 
  {
    "count": "510", 
    "page": "Hatfield\u2013McCoy feud"
  }, 
  {
    "count": "509", 
    "page": "Drakensberg"
  }, 
  {
    "count": "509", 
    "page": "Anne Hathaway (actress)"
  }, 
  {
    "count": "507", 
    "page": "One Tree Hill (TV series)"
  }, 
  {
    "count": "507", 
    "page": "Kid Cudi"
  }, 
  {
    "count": "507", 
    "page": "Fynbos"
  }, 
  {
    "count": "507", 
    "page": "Franklin D. Roosevelt"
  }, 
  {
    "count": "507", 
    "page": "Drew Barrymore"
  }, 
  {
    "count": "507", 
    "page": "American Horror Story"
  }, 
  {
    "count": "506", 
    "page": "President of the United States"
  }, 
  {
    "count": "506", 
    "page": "John Cazale"
  }, 
  {
    "count": "505", 
    "page": "Supernatural (season 7)"
  }, 
  {
    "count": "505", 
    "page": "Special:Randompage"
  }, 
  {
    "count": "505", 
    "page": "Prometheus (film)"
  }, 
  {
    "count": "504", 
    "page": "Save China's Tigers"
  }, 
  {
    "count": "503", 
    "page": "Skins (TV series)"
  }, 
  {
    "count": "503", 
    "page": "Corned beef"
  }, 
  {
    "count": "502", 
    "page": "Vulva"
  }, 
  {
    "count": "502", 
    "page": "List of The Vampire Diaries episodes"
  }, 
  {
    "count": "502", 
    "page": "Israel"
  }, 
  {
    "count": "502", 
    "page": "Footloose"
  }, 
  {
    "count": "502", 
    "page": "Florence and the Machine"
  }, 
  {
    "count": "501", 
    "page": "James Bond"
  }, 
  {
    "count": "500", 
    "page": "Neil deGrasse Tyson"
  }, 
  {
    "count": "500", 
    "page": "Kurt Cobain"
  }, 
  {
    "count": "499", 
    "page": "Talia Shire"
  }, 
  {
    "count": "499", 
    "page": "Iran"
  }, 
  {
    "count": "498", 
    "page": "search-ltr.png"
  }, 
  {
    "count": "498", 
    "page": "Amber Tamblyn"
  }, 
  {
    "count": "497", 
    "page": "magnify-clip.png"
  }, 
  {
    "count": "497", 
    "page": "Pinterest"
  }, 
  {
    "count": "496", 
    "page": "Twilight (series)"
  }, 
  {
    "count": "496", 
    "page": "Power Girl"
  }, 
  {
    "count": "496", 
    "page": "NCIS (TV series)"
  }, 
  {
    "count": "496", 
    "page": "List of The Big Bang Theory episodes (season 5)"
  }, 
  {
    "count": "496", 
    "page": "File:Teigan Van Roosmalen.jpg"
  }, 
  {
    "count": "495", 
    "page": "Salma Hayek"
  }, 
  {
    "count": "494", 
    "page": "Jonah Hill"
  }, 
  {
    "count": "493", 
    "page": "William Shakespeare"
  }, 
  {
    "count": "493", 
    "page": "Pink Friday: Roman Reloaded"
  }, 
  {
    "count": "492", 
    "page": "Kelly Clarkson"
  }, 
  {
    "count": "491", 
    "page": "M-Audio"
  }, 
  {
    "count": "491", 
    "page": "Jousting"
  }, 
  {
    "count": "491", 
    "page": "Avatar (2009 film)"
  }, 
  {
    "count": "490", 
    "page": "Ten Commandments"
  }, 
  {
    "count": "490", 
    "page": "Danica Patrick"
  }, 
  {
    "count": "489", 
    "page": "The Rum Diary (film)"
  }, 
  {
    "count": "489", 
    "page": "Boardwalk Empire"
  }, 
  {
    "count": "488", 
    "page": "Mexico"
  }, 
  {
    "count": "488", 
    "page": "Friends"
  }, 
  {
    "count": "488", 
    "page": "Bridesmaids (2011 film)"
  }, 
  {
    "count": "488", 
    "page": "Absinthe"
  }, 
  {
    "count": "487", 
    "page": "Jay Bilas"
  }, 
  {
    "count": "487", 
    "page": "Desperate Housewives"
  }, 
  {
    "count": "486", 
    "page": "Contagion (film)"
  }, 
  {
    "count": "485", 
    "page": "Bipolar disorder"
  }, 
  {
    "count": "484", 
    "page": "Tramadol"
  }, 
  {
    "count": "484", 
    "page": "Orgasm"
  }, 
  {
    "count": "484", 
    "page": "Mia Wasikowska"
  }, 
  {
    "count": "483", 
    "page": "The Amazing Spider-Man (2012 film)"
  }, 
  {
    "count": "482", 
    "page": "Gorillaz"
  }, 
  {
    "count": "481", 
    "page": "The Hunger Games trilogy"
  }, 
  {
    "count": "481", 
    "page": "Special:RecentChanges"
  }, 
  {
    "count": "481", 
    "page": "No Reserve"
  }, 
  {
    "count": "481", 
    "page": "Bob McAdoo"
  }, 
  {
    "count": "480", 
    "page": "Quinoa"
  }, 
  {
    "count": "480", 
    "page": "Mary Beth Harshbarger"
  }, 
  {
    "count": "477", 
    "page": "Jackie Chan"
  }, 
  {
    "count": "477", 
    "page": "Diane Keaton"
  }, 
  {
    "count": "476", 
    "page": "Hotmail"
  }, 
  {
    "count": "475", 
    "page": "The Black Keys"
  }, 
  {
    "count": "475", 
    "page": "Martin Luther King, Jr."
  }, 
  {
    "count": "475", 
    "page": "Kimbra"
  }, 
  {
    "count": "475", 
    "page": "Jill Wagner"
  }, 
  {
    "count": "475", 
    "page": "Hawkeye (comics)"
  }, 
  {
    "count": "475", 
    "page": "Fisker Karma"
  }, 
  {
    "count": "475", 
    "page": "Cameron Diaz"
  }, 
  {
    "count": "474", 
    "page": "Usher (entertainer)"
  }, 
  {
    "count": "474", 
    "page": "Tim Burton"
  }, 
  {
    "count": "474", 
    "page": "Phineas and Ferb"
  }, 
  {
    "count": "474", 
    "page": "Led Zeppelin"
  }, 
  {
    "count": "474", 
    "page": "Kunal Nayyar"
  }, 
  {
    "count": "473", 
    "page": "Magic Johnson"
  }, 
  {
    "count": "472", 
    "page": "Eye color"
  }, 
  {
    "count": "472", 
    "page": "David Guetta"
  }, 
  {
    "count": "472", 
    "page": "[object Object]://www.bflix.info/worker/init.js"
  }, 
  {
    "count": "471", 
    "page": "Prince (musician)"
  }, 
  {
    "count": "471", 
    "page": "Metallica"
  }, 
  {
    "count": "471", 
    "page": "Charles Lindbergh"
  }, 
  {
    "count": "470", 
    "page": "The Twilight Saga: Breaking Dawn"
  }, 
  {
    "count": "470", 
    "page": "Narwhal"
  }, 
  {
    "count": "470", 
    "page": "List of New Girl episodes"
  }, 
  {
    "count": "470", 
    "page": "John Gotti"
  }, 
  {
    "count": "470", 
    "page": "Gossip Girl"
  }, 
  {
    "count": "469", 
    "page": "Woody Allen"
  }, 
  {
    "count": "469", 
    "page": "The Police"
  }, 
  {
    "count": "468", 
    "page": "Vanessa Hudgens"
  }, 
  {
    "count": "468", 
    "page": "Sparkle (1976 film)"
  }, 
  {
    "count": "468", 
    "page": "Justice League: Doom"
  }, 
  {
    "count": "468", 
    "page": "Hunter S. Thompson"
  }, 
  {
    "count": "467", 
    "page": "Dragon Ball"
  }, 
  {
    "count": "466", 
    "page": "The Muppets (film)"
  }, 
  {
    "count": "466", 
    "page": "List of countries by population"
  }, 
  {
    "count": "466", 
    "page": "Lichtenberg figure"
  }, 
  {
    "count": "466", 
    "page": "Leap year"
  }, 
  {
    "count": "465", 
    "page": "Young Adult (film)"
  }, 
  {
    "count": "465", 
    "page": "The Simpsons"
  }, 
  {
    "count": "465", 
    "page": "Tar Heel"
  }, 
  {
    "count": "465", 
    "page": "Jennifer Garner"
  }, 
  {
    "count": "464", 
    "page": "Personal life of Wilt Chamberlain"
  }, 
  {
    "count": "463", 
    "page": "Rene Russo"
  }, 
  {
    "count": "463", 
    "page": "Cocaine"
  }, 
  {
    "count": "462", 
    "page": "True Blood"
  }, 
  {
    "count": "462", 
    "page": "Sean Bean"
  }, 
  {
    "count": "462", 
    "page": "Leonardo da Vinci"
  }, 
  {
    "count": "462", 
    "page": "Cobie Smulders"
  }, 
  {
    "count": "462", 
    "page": "Adrienne Bailon"
  }, 
  {
    "count": "461", 
    "page": "Sean Connery"
  }, 
  {
    "count": "461", 
    "page": "England"
  }, 
  {
    "count": "461", 
    "page": "Criminal Minds"
  }, 
  {
    "count": "460", 
    "page": "The Vampire Diaries (season 3)"
  }, 
  {
    "count": "460", 
    "page": "List of pornographic actresses by decade"
  }, 
  {
    "count": "460", 
    "page": "John Lennon"
  }, 
  {
    "count": "459", 
    "page": "The Texas Chainsaw Massacre"
  }, 
  {
    "count": "459", 
    "page": "Kesha"
  }, 
  {
    "count": "458", 
    "page": "Lionel Messi"
  }, 
  {
    "count": "458", 
    "page": "Acoustic Electric Guitar"
  }, 
  {
    "count": "457", 
    "page": "Apple Inc."
  }, 
  {
    "count": "456", 
    "page": "Paul McCartney"
  }, 
  {
    "count": "456", 
    "page": "Jesus"
  }, 
  {
    "count": "456", 
    "page": "Jake Gyllenhaal"
  }, 
  {
    "count": "456", 
    "page": "Despicable Me"
  }, 
  {
    "count": "456", 
    "page": "2012 Summer Olympics"
  }, 
  {
    "count": "455", 
    "page": "Jean-Claude Van Damme"
  }, 
  {
    "count": "455", 
    "page": "Avan Jogia"
  }, 
  {
    "count": "454", 
    "page": "Singapore"
  }, 
  {
    "count": "454", 
    "page": "Patrick Swayze"
  }, 
  {
    "count": "454", 
    "page": "Paan Singh Tomar"
  }, 
  {
    "count": "454", 
    "page": "Hard Candy (film)"
  }, 
  {
    "count": "454", 
    "page": "Dream House (film)"
  }, 
  {
    "count": "454", 
    "page": "Being Human (TV series)"
  }, 
  {
    "count": "454", 
    "page": "Ashton Kutcher"
  }, 
  {
    "count": "453", 
    "page": "Samurai"
  }, 
  {
    "count": "453", 
    "page": "Jean-Marc Mormeck"
  }, 
  {
    "count": "452", 
    "page": "Michael Fassbender"
  }, 
  {
    "count": "452", 
    "page": "Home Improvement (TV series)"
  }, 
  {
    "count": "452", 
    "page": "Goon (film)"
  }, 
  {
    "count": "452", 
    "page": "Charles Manson"
  }, 
  {
    "count": "451", 
    "page": "Schizophrenia"
  }, 
  {
    "count": "451", 
    "page": "Jim Carrey"
  }, 
  {
    "count": "451", 
    "page": "Hawaii"
  }, 
  {
    "count": "451", 
    "page": "Green Day"
  }, 
  {
    "count": "451", 
    "page": "Dakota Fanning"
  }, 
  {
    "count": "451", 
    "page": "B\u00e9r\u00e9nice Bejo"
  }, 
  {
    "count": "451", 
    "page": "Arsenal F.C."
  }, 
  {
    "count": "450", 
    "page": "Kate Smith"
  }, 
  {
    "count": "450", 
    "page": "Inception"
  }, 
  {
    "count": "450", 
    "page": "Capybara"
  }, 
  {
    "count": "449", 
    "page": "Help:Searching"
  }, 
  {
    "count": "449", 
    "page": "Astrological sign"
  }, 
  {
    "count": "448", 
    "page": "Poppy Montgomery"
  }, 
  {
    "count": "448", 
    "page": "Kowloon Walled City"
  }, 
  {
    "count": "447", 
    "page": "Purim"
  }, 
  {
    "count": "447", 
    "page": "Michael Corleone"
  }, 
  {
    "count": "447", 
    "page": "Joseph Stalin"
  }, 
  {
    "count": "447", 
    "page": "Dubai"
  }, 
  {
    "count": "447", 
    "page": "Bill Gates"
  }, 
  {
    "count": "446", 
    "page": "Theodore Roosevelt"
  }, 
  {
    "count": "446", 
    "page": "Digital object identifier"
  }, 
  {
    "count": "446", 
    "page": "Ash Wednesday"
  }, 
  {
    "count": "446", 
    "page": "Anjelica Huston"
  }, 
  {
    "count": "445", 
    "page": "September 11 attacks"
  }, 
  {
    "count": "445", 
    "page": "Bed size"
  }, 
  {
    "count": "444", 
    "page": "Game of Thrones (season 2)"
  }, 
  {
    "count": "444", 
    "page": "California"
  }, 
  {
    "count": "444", 
    "page": "Brave (2012 film)"
  }, 
  {
    "count": "443", 
    "page": "Thor (film)"
  }, 
  {
    "count": "443", 
    "page": "Slash (musician)"
  }, 
  {
    "count": "443", 
    "page": "Robert Duvall"
  }, 
  {
    "count": "442", 
    "page": "Terry Crews"
  }, 
  {
    "count": "442", 
    "page": "Star Trek: The Next Generation"
  }, 
  {
    "count": "442", 
    "page": "Orson Bean"
  }, 
  {
    "count": "442", 
    "page": "Enrollment Act"
  }, 
  {
    "count": "442", 
    "page": "Dave Navarro"
  }, 
  {
    "count": "442", 
    "page": "Bill Clinton"
  }, 
  {
    "count": "441", 
    "page": "Timothy Olyphant"
  }, 
  {
    "count": "441", 
    "page": "Sia Furler"
  }, 
  {
    "count": "441", 
    "page": "OFWGKTA"
  }, 
  {
    "count": "441", 
    "page": "List of Strikeforce events"
  }, 
  {
    "count": "441", 
    "page": "List of Merlin episodes"
  }, 
  {
    "count": "441", 
    "page": "Joseph Gordon-Levitt"
  }, 
  {
    "count": "441", 
    "page": "Jason Segel"
  }, 
  {
    "count": "441", 
    "page": "Gina Carano"
  }, 
  {
    "count": "440", 
    "page": "wikimedia-button.png"
  }, 
  {
    "count": "440", 
    "page": "The Adventures of Tintin"
  }, 
  {
    "count": "439", 
    "page": "Chris Penn"
  }, 
  {
    "count": "438", 
    "page": "Take Care"
  }, 
  {
    "count": "438", 
    "page": "Julia Roberts"
  }, 
  {
    "count": "438", 
    "page": "David Bailey (photographer)"
  }, 
  {
    "count": "437", 
    "page": "Sofia Coppola"
  }, 
  {
    "count": "436", 
    "page": "The Invention of Hugo Cabret"
  }, 
  {
    "count": "436", 
    "page": "Pok\u00e9mon"
  }, 
  {
    "count": "436", 
    "page": "Pirates of the Caribbean: On Stranger Tides"
  }, 
  {
    "count": "436", 
    "page": "Pierce Brosnan"
  }, 
  {
    "count": "436", 
    "page": "Miranda Lambert"
  }, 
  {
    "count": "436", 
    "page": "Buffalo buffalo"
  }, 
  {
    "count": "435", 
    "page": "Tepui"
  }, 
  {
    "count": "435", 
    "page": "Taylor Kitsch"
  }, 
  {
    "count": "435", 
    "page": "Matt Damon"
  }, 
  {
    "count": "435", 
    "page": "Bane (comics)"
  }, 
  {
    "count": "435", 
    "page": "Amber Heard"
  }, 
  {
    "count": "434", 
    "page": "Shakira"
  }, 
  {
    "count": "434", 
    "page": "Sarah Jessica Parker"
  }, 
  {
    "count": "434", 
    "page": "Nirvana (band)"
  }, 
  {
    "count": "432", 
    "page": "Real Steel"
  }, 
  {
    "count": "432", 
    "page": "Methamphetamine"
  }, 
  {
    "count": "431", 
    "page": "UFC on Fox: Diaz vs. Miller"
  }, 
  {
    "count": "431", 
    "page": "Richard Nixon"
  }, 
  {
    "count": "431", 
    "page": "Marshall Plumlee"
  }, 
  {
    "count": "431", 
    "page": "Equinox"
  }, 
  {
    "count": "430", 
    "page": "David Cross"
  }, 
  {
    "count": "429", 
    "page": "SpongeBob SquarePants"
  }, 
  {
    "count": "428", 
    "page": "Radiohead"
  }, 
  {
    "count": "428", 
    "page": "New Zealand"
  }, 
  {
    "count": "428", 
    "page": "Marilyn Manson"
  }, 
  {
    "count": "428", 
    "page": "Balto"
  }, 
  {
    "count": "427", 
    "page": "Wikipedia:Citation needed"
  }, 
  {
    "count": "427", 
    "page": "Katniss Everdeen"
  }, 
  {
    "count": "427", 
    "page": "Alyson Hannigan"
  }, 
  {
    "count": "426", 
    "page": "Underworld (film series)"
  }, 
  {
    "count": "426", 
    "page": "Fellatio"
  }, 
  {
    "count": "425", 
    "page": "Village People"
  }, 
  {
    "count": "424", 
    "page": "Mick Jagger"
  }, 
  {
    "count": "424", 
    "page": "Lou Ferrigno"
  }, 
  {
    "count": "424", 
    "page": "Los Angeles"
  }, 
  {
    "count": "424", 
    "page": "George Harrison"
  }, 
  {
    "count": "424", 
    "page": "Earth"
  }, 
  {
    "count": "423", 
    "page": "Batman Begins"
  }, 
  {
    "count": "422", 
    "page": "Wikipedia:Articles for creation"
  }, 
  {
    "count": "422", 
    "page": "Underworld: Awakening"
  }, 
  {
    "count": "422", 
    "page": "Kate Beckinsale"
  }, 
  {
    "count": "422", 
    "page": "Julianne Hough"
  }, 
  {
    "count": "422", 
    "page": "Jessie J"
  }, 
  {
    "count": "422", 
    "page": "Dr. Dre"
  }, 
  {
    "count": "422", 
    "page": "Dell Curry"
  }, 
  {
    "count": "422", 
    "page": "2002 Oakland Athletics season"
  }, 
  {
    "count": "421", 
    "page": "Zodiac"
  }, 
  {
    "count": "421", 
    "page": "Sherlock Holmes"
  }, 
  {
    "count": "421", 
    "page": "List of PlayStation Vita games"
  }, 
  {
    "count": "420", 
    "page": "Thomas Jefferson"
  }, 
  {
    "count": "420", 
    "page": "Suits (TV series)"
  }, 
  {
    "count": "420", 
    "page": "Jamie Lee Curtis"
  }, 
  {
    "count": "420", 
    "page": "Harrison Ford"
  }, 
  {
    "count": "420", 
    "page": "Che Guevara"
  }, 
  {
    "count": "419", 
    "page": "IPhone"
  }, 
  {
    "count": "419", 
    "page": "Black Widow (Natalia Romanova)"
  }, 
  {
    "count": "418", 
    "page": "List of Star Wars: The Clone Wars episodes"
  }, 
  {
    "count": "418", 
    "page": "Hong Kong"
  }, 
  {
    "count": "418", 
    "page": "Daniel Craig"
  }, 
  {
    "count": "417", 
    "page": "Stacy Keibler"
  }, 
  {
    "count": "417", 
    "page": "Solar System"
  }, 
  {
    "count": "417", 
    "page": "Sandra Bullock"
  }, 
  {
    "count": "417", 
    "page": "Joker (comics)"
  }, 
  {
    "count": "417", 
    "page": "America's Next Top Model"
  }, 
  {
    "count": "416", 
    "page": "Newt Gingrich"
  }, 
  {
    "count": "416", 
    "page": "Dwyane Wade"
  }, 
  {
    "count": "416", 
    "page": "Andy Warhol"
  }, 
  {
    "count": "415", 
    "page": "Martin Sheen"
  }, 
  {
    "count": "415", 
    "page": "Danny DeVito"
  }, 
  {
    "count": "415", 
    "page": "Columbine High School massacre"
  }, 
  {
    "count": "415", 
    "page": "Chris Evans (actor)"
  }, 
  {
    "count": "414", 
    "page": "Zach Galifianakis"
  }, 
  {
    "count": "414", 
    "page": "Mission: Impossible \u2013 Ghost Protocol"
  }, 
  {
    "count": "414", 
    "page": "List of Ben 10: Ultimate Alien episodes"
  }, 
  {
    "count": "414", 
    "page": "Kane (wrestler)"
  }, 
  {
    "count": "414", 
    "page": "Amy Winehouse"
  }, 
  {
    "count": "413", 
    "page": "North Korea and weapons of mass destruction"
  }, 
  {
    "count": "413", 
    "page": "Gang Saw"
  }, 
  {
    "count": "412", 
    "page": "Jason Statham"
  }, 
  {
    "count": "412", 
    "page": "Hayao Miyazaki"
  }, 
  {
    "count": "412", 
    "page": "Genevieve Gorder"
  }, 
  {
    "count": "412", 
    "page": "Eva Mendes"
  }, 
  {
    "count": "411", 
    "page": "Zlatan Ibrahimovi\u0107"
  }, 
  {
    "count": "411", 
    "page": "Soviet Union"
  }, 
  {
    "count": "411", 
    "page": "Mac Miller"
  }, 
  {
    "count": "411", 
    "page": "Hinamatsuri"
  }, 
  {
    "count": "411", 
    "page": "Anderson Cooper"
  }, 
  {
    "count": "410", 
    "page": "Washington Republican caucuses, 2012"
  }, 
  {
    "count": "410", 
    "page": "United States presidential election, 2012"
  }, 
  {
    "count": "410", 
    "page": "List of Archer episodes"
  }, 
  {
    "count": "410", 
    "page": "Iceland"
  }, 
  {
    "count": "409", 
    "page": "Roger Federer"
  }, 
  {
    "count": "409", 
    "page": "Benedict Cumberbatch"
  }, 
  {
    "count": "408", 
    "page": "The Andrews Sisters"
  }, 
  {
    "count": "408", 
    "page": "Red Hot Chili Peppers"
  }, 
  {
    "count": "408", 
    "page": "Pablo Picasso"
  }, 
  {
    "count": "408", 
    "page": "Magnify-clip.png"
  }, 
  {
    "count": "408", 
    "page": "Eric Roberts"
  }, 
  {
    "count": "408", 
    "page": "2012 Big East Men's Basketball Tournament"
  }, 
  {
    "count": "407", 
    "page": "Macaulay Culkin"
  }, 
  {
    "count": "407", 
    "page": "Lion"
  }, 
  {
    "count": "407", 
    "page": "Italy"
  }, 
  {
    "count": "407", 
    "page": "Greek alphabet"
  }, 
  {
    "count": "407", 
    "page": "Firefly (TV series)"
  }, 
  {
    "count": "407", 
    "page": "Alex O'Loughlin"
  }, 
  {
    "count": "405", 
    "page": "Steven Tyler"
  }, 
  {
    "count": "405", 
    "page": "Steve McQueen"
  }, 
  {
    "count": "405", 
    "page": "Search"
  }, 
  {
    "count": "405", 
    "page": "Oxycodone"
  }
]
